Backup/__init__.py
Backup/Bridge-Tools-master/__init__.py
Backup/Bridge-Tools-master/autorever.py
Backup/Bridge-Tools-master/bridgetools.py
Backup/Bridge-Tools-master/ratingtools.py
Backup/Bridge-Tools-master/vuextractor.py
Backup/Cmd/__init__.py
Backup/Code-For-Future-Restore_Cube/Restore_Cube.py
Backup/Code-For-Future-Restore_Cube/__init__.py
Backup/EdpBriage-master/__init__.py
Backup/EdpBriage-master/run.py
Backup/EdpBriage-master/src/__init__.py
Backup/EdpBriage-master/src/bridge.py
Backup/EdpBriage-master/src/card.py
Backup/EdpBriage-master/src/deck.py
Backup/EdpBriage-master/src/errors.py
Backup/EdpBriage-master/src/player.py
Backup/EdpBriage-master/src/pycb.py
Backup/EdpBriage-master/tests/__init__.py
Backup/EdpBriage-master/tests/test_card.py
Backup/EdpBriage-master/tests/test_hand.py
Backup/Fluent Python/__init__.py
Backup/Head First Python/__init__.py
Backup/Leetcode/001_链表反转_迭代.py
Backup/Leetcode/__init__.py
Backup/Leetcode/a.py
Backup/Leetcode/b.py
Backup/Leetcode/tempCodeRunnerFile.py
Backup/Leetcode/test_1_两数之和.py
Backup/Leetcode/test_2_两数相加.py
Backup/Object/__init__.py
Backup/Object/人狗大战.py
Backup/Object/单例模式.py
Backup/Object/师傅徒弟.py
Backup/Object/异常.py
Backup/Object/搬家具.py
Backup/Object/烤地瓜.py
Backup/Others/__init__.py
Backup/Others/雷电/__init__.py
Backup/Others/雷电/main.py
Backup/Others/雷电/sounds/__init__.py
Backup/Others/雷电/图片/__init__.py
Backup/Python-100-Days-master/__init__.py
Backup/Spider/__init__.py
Backup/Spider/Spider/__init__.py
Backup/Spider/Spider/items.py
Backup/Spider/Spider/middlewares.py
Backup/Spider/Spider/pipelines.py
Backup/Spider/Spider/settings.py
Backup/Spider/Spider/spiders/__init__.py
Backup/Spider/Spider/spiders/itcast.py
Backup/SpiderBook-master/__init__.py
Backup/Tensorflow/__init__.py
Backup/Tensorflow/autograd.py
Backup/Tensorflow/gpu_accelerate.py
Backup/Testcase/__init__.py
Backup/Testcase/conftest.py
Backup/Testcase/test_lib.py
Backup/Testcase/test_matrix.py
Backup/Testcase/test_vector.py
Backup/Tools/__init__.py
jasonqwu-0.0.8.dist-info/METADATA
jasonqwu-0.0.8.dist-info/WHEEL
jasonqwu-0.0.8.dist-info/license.txt
jasonqwu-0.0.8.dist-info/top_level.txt
jasonqwu-0.0.8.dist-info/RECORD
