Metadata-Version: 2.1
Name: jasonqwu
Version: 0.0.8
Summary: 这是 jasonqwu 的库
Home-page: https://github.com/jasonqwu/Python_code
Author: Jason Q. Wu
Author-email: jasonqwu@qq.com
License: MIT
License-File: license.txt
